{
  "manifestVersion": "3.2",
  "proxies": [
    {
      "address": "0x41D7935C6D733De81C24982929a15B07991738fB",
      "txHash": "0xc17cb3c1d64b68106479eec4eeceefa8bfdce4092449469e17a99886036ee44c",
      "kind": "transparent"
    }
  ],
  "impls": {
    "7675dfba73362e7c8833cf4e2bf71076740b99e4be11ee21111c947534434bce": {
      "address": "0x87a02957F7AdAA7a0c31237443a964d3bfc2Bb9F",
      "txHash": "0xeda63c35859ecdb783dd0a4b752b50e6a7dc5ec8fb383a8740ea1d30f5c4e5ea",
      "layout": {
        "solcVersion": "0.8.26",
        "storage": [],
        "types": {
          "t_bool": {
            "label": "bool",
            "numberOfBytes": "1"
          },
          "t_struct(InitializableStorage)64_storage": {
            "label": "struct Initializable.InitializableStorage",
            "members": [
              {
                "label": "_initialized",
                "type": "t_uint64",
                "offset": 0,
                "slot": "0"
              },
              {
                "label": "_initializing",
                "type": "t_bool",
                "offset": 8,
                "slot": "0"
              }
            ],
            "numberOfBytes": "32"
          },
          "t_uint64": {
            "label": "uint64",
            "numberOfBytes": "8"
          }
        },
        "namespaces": {
          "erc7201:openzeppelin.storage.Initializable": [
            {
              "contract": "Initializable",
              "label": "_initialized",
              "type": "t_uint64",
              "src": "@openzeppelin/contracts-upgradeable/proxy/utils/Initializable.sol:69",
              "offset": 0,
              "slot": "0"
            },
            {
              "contract": "Initializable",
              "label": "_initializing",
              "type": "t_bool",
              "src": "@openzeppelin/contracts-upgradeable/proxy/utils/Initializable.sol:73",
              "offset": 8,
              "slot": "0"
            }
          ]
        }
      }
    }
  }
}
